tut_langgraph/t0_reference_demo/.gitignore
tut_langgraph/t0_reference_demo/.loaded_files
tut_langgraph/t0_reference_demo/audit_data_monitor.log
tut_langgraph/t0_reference_demo/campaign_generator_20241124.log
tut_langgraph/t0_reference_demo/chapter1/ai_agents.png
tut_langgraph/t0_reference_demo/chapter1/graph_8717.png
tut_langgraph/t0_reference_demo/chapter1/lesson1.py
tut_langgraph/t0_reference_demo/chapter10/display_graph.py
tut_langgraph/t0_reference_demo/chapter10/lesson10a.py
tut_langgraph/t0_reference_demo/chapter10/lesson10b.py
tut_langgraph/t0_reference_demo/chapter10/lesson10c.py
tut_langgraph/t0_reference_demo/chapter10/lesson10d.py
tut_langgraph/t0_reference_demo/chapter10/lesson10e.py
tut_langgraph/t0_reference_demo/chapter10/test.py
tut_langgraph/t0_reference_demo/chapter11/display_graph.py
tut_langgraph/t0_reference_demo/chapter11/Faiss by FacebookAI.pdf
tut_langgraph/t0_reference_demo/chapter11/lesson11.i.py
tut_langgraph/t0_reference_demo/chapter11/lesson11a.py
tut_langgraph/t0_reference_demo/chapter11/lesson11b.py
tut_langgraph/t0_reference_demo/chapter11/lesson11c.py
tut_langgraph/t0_reference_demo/chapter11/lesson11d.py
tut_langgraph/t0_reference_demo/chapter11/lesson11e.py
tut_langgraph/t0_reference_demo/chapter11/lesson11f.py
tut_langgraph/t0_reference_demo/chapter11/lesson11g.py
tut_langgraph/t0_reference_demo/chapter11/lesson11h.py
tut_langgraph/t0_reference_demo/chapter12/display_graph.py
tut_langgraph/t0_reference_demo/chapter12/lesson12a.py
tut_langgraph/t0_reference_demo/chapter12/lesson12b.py
tut_langgraph/t0_reference_demo/chapter12/lesson12c.py
tut_langgraph/t0_reference_demo/chapter12/lesson12d.py
tut_langgraph/t0_reference_demo/chapter13/audit_data/account_reconciliations.csv
tut_langgraph/t0_reference_demo/chapter13/audit_data/accounts_payable_receivable.csv
tut_langgraph/t0_reference_demo/chapter13/audit_data/asset_purchase_invoices.csv
tut_langgraph/t0_reference_demo/chapter13/audit_data/balance_sheet.csv
tut_langgraph-0.1.1.dist-info/entry_points.txt
tut_langgraph-0.1.1.dist-info/METADATA
tut_langgraph-0.1.1.dist-info/WHEEL
tut_langgraph-0.1.1.dist-info/RECORD
