Metadata-Version: 2.3
Name: tut-langgraph
Version: 0.1.1
Summary: Add your description here
Author: libin
Author-email: xjd.binlee@qq.com
Requires-Python: >=3.12
Classifier: Programming Language :: Python :: 3
Classifier: Programming Language :: Python :: 3.12
Classifier: Programming Language :: Python :: 3.13
Requires-Dist: arxiv (>=2.2.0)
Requires-Dist: eventlet (>=0.40.0)
Requires-Dist: faker (>=37.3.0)
Requires-Dist: flask (>=3.1.1)
Requires-Dist: flask-cors (>=6.0.0)
Requires-Dist: flask-socketio (>=5.5.1)
Requires-Dist: gradio (>=5.33.0)
Requires-Dist: ipython (>=9.3.0)
Requires-Dist: jupyter (>=1.1.1)
Requires-Dist: langchain (>=0.3.25)
Requires-Dist: langchain-chroma (>=0.2.4)
Requires-Dist: langchain-community (>=0.3.24)
Requires-Dist: langchain-deepseek (>=0.1.3)
Requires-Dist: langchain-experimental (>=0.3.4)
Requires-Dist: langchain-google-genai (>=2.1.5)
Requires-Dist: langchain-mcp-adapters (>=0.1.4)
Requires-Dist: langchain-nvidia-ai-endpoints (>=0.3.10)
Requires-Dist: langchain-openai (>=0.3.19)
Requires-Dist: langgraph (>=0.4.8)
Requires-Dist: loguru (>=0.7.3)
Requires-Dist: mcp (>=1.9.2)
Requires-Dist: pandas (>=2.3.0)
Requires-Dist: pathlib (>=1.0.1)
Requires-Dist: psycopg2-binary (>=2.9.10)
Requires-Dist: seaborn (>=0.13.2)
Requires-Dist: textblob (>=0.19.0)
Requires-Dist: watchdog (>=6.0.0)
Requires-Dist: yfinance (>=0.2.61)
